trustra/__init__.py
trustra/core.py
trustra/dashboard.py
trustra/fairness.py
trustra/reporter.py
trustra/trainer.py
trustra/validator.py
trustra-1.0.0.dist-info/licenses/LICENSE
trustra-1.0.0.dist-info/METADATA
trustra-1.0.0.dist-info/WHEEL
trustra-1.0.0.dist-info/top_level.txt
trustra-1.0.0.dist-info/RECORD
