Metadata-Version: 2.4
Name: trustra
Version: 1.0.0
Summary: Trust-first AutoML: Automated ML with built-in fairness, drift, and reliability.
Home-page: https://github.com/Devansh-567/Trustra---Trust-First-AutoML-Framework
Author: Devansh Singh
Author-email: devansh.jay.singh@gmail.com
Project-URL: Documentation, https://github.com/Devansh-567/Trustra---Trust-First-AutoML-Framework#readme
Project-URL: Source, https://github.com/Devansh-567/Trustra---Trust-First-AutoML-Framework
Project-URL: Tracker, https://github.com/Devansh-567/Trustra---Trust-First-AutoML-Framework/issues
Keywords: automl,fairness,bias,drift,explainability,machine-learning,responsible-ai
Classifier: Development Status :: 4 - Beta
Classifier: Intended Audience :: Developers
Classifier: Intended Audience :: Science/Research
Classifier: License :: OSI Approved :: MIT License
Classifier: Programming Language :: Python :: 3
Classifier: Programming Language :: Python :: 3.9
Classifier: Programming Language :: Python :: 3.10
Classifier: Programming Language :: Python :: 3.11
Classifier: Topic :: Scientific/Engineering :: Artificial Intelligence
Classifier: Topic :: Software Development :: Libraries :: Python Modules
Requires-Python: >=3.9
License-File: LICENSE
Requires-Dist: pandas>=1.5
Requires-Dist: numpy>=1.21
Requires-Dist: scikit-learn>=1.3
Requires-Dist: optuna>=3.0
Requires-Dist: plotly>=5.10
Requires-Dist: jinja2>=3.1
Requires-Dist: fairlearn>=0.10
Requires-Dist: xgboost>=1.7
Dynamic: author
Dynamic: author-email
Dynamic: classifier
Dynamic: description
Dynamic: description-content-type
Dynamic: home-page
Dynamic: keywords
Dynamic: license-file
Dynamic: project-url
Dynamic: requires-dist
Dynamic: requires-python
Dynamic: summary
